clickhouse_ddl/ClickHouseDDL.py
clickhouse_ddl/Config.py
clickhouse_ddl/Function.py
clickhouse_ddl/__init__.py
clickhouse_ddl-1.0.6.dist-info/LICENSE
clickhouse_ddl-1.0.6.dist-info/METADATA
clickhouse_ddl-1.0.6.dist-info/WHEEL
clickhouse_ddl-1.0.6.dist-info/top_level.txt
clickhouse_ddl-1.0.6.dist-info/RECORD
