Metadata-Version: 2.1
Name: clickhouse-ddl
Version: 1.0.6
Summary: Clickhouse metadata (DDL) grabber
Home-page: https://github.com/ish1mura/clickhouse_ddl
Author: ish1mura
Author-email: ek.dummy@gmail.com
Classifier: Programming Language :: Python :: 3
Classifier: License :: OSI Approved :: MIT License
Classifier: Operating System :: OS Independent
License-File: LICENSE
Requires-Dist: clickhouse-driver
